double_indent.py
double_indent-0.1.5.dist-info/LICENCE
double_indent-0.1.5.dist-info/METADATA
double_indent-0.1.5.dist-info/WHEEL
double_indent-0.1.5.dist-info/entry_points.txt
double_indent-0.1.5.dist-info/top_level.txt
double_indent-0.1.5.dist-info/RECORD
