Metadata-Version: 2.1
Name: double_indent
Version: 0.1.5
Summary: a code formatter indenting function and method definitions twice
Home-page: https://github.com/jkittner/double-indent
Author: Jonas Kittner
Author-email: jkittner@users.noreply.github.com
License: MIT
Classifier: License :: OSI Approved :: MIT License
Classifier: Programming Language :: Python :: 3
Classifier: Programming Language :: Python :: 3 :: Only
Classifier: Programming Language :: Python :: Implementation :: CPython
Requires-Python: >=3.8
License-File: LICENCE
Requires-Dist: tokenize-rt
